{
  "GlobalConfiguration": {
    "BaseUrl": "https://localhost:7000"
  },
  "Routes": [
    {
      "UpstreamPathTemplate": "/gateway/trip",
      "UpstreamHttpMethod": [ "post" ],
      "DownstreamPathTemplate": "/Trips",
      "DownstreamScheme": "https",
      "DownstreamHostAndPorts": [
        {
          "Host": "localhost",
          "Port": "7001"
        }
      ]
    },
    {
      "UpstreamPathTemplate": "/gateway/trip",
      "UpstreamHttpMethod": [ "put" ],
      "DownstreamPathTemplate": "/Trips",
      "DownstreamScheme": "https",
      "DownstreamHostAndPorts": [
        {
          "Host": "localhost",
          "Port": "7001"
        }
      ]
    },
    {
      "UpstreamPathTemplate": "/gateway/trip/visibility",
      "UpstreamHttpMethod": [ "put" ],
      "DownstreamPathTemplate": "/Trips/Visibility",
      "DownstreamScheme": "https",
      "DownstreamHostAndPorts": [
        {
          "Host": "localhost",
          "Port": "7001"
        }
      ]
    },
    {
      "UpstreamPathTemplate": "/gateway/trip/publish",
      "UpstreamHttpMethod": [ "put" ],
      "DownstreamPathTemplate": "/Trips/publish",
      "DownstreamScheme": "https",
      "DownstreamHostAndPorts": [
        {
          "Host": "localhost",
          "Port": "7001"
        }
      ]
    },
    {
      "UpstreamPathTemplate": "/gateway/trip",
      "UpstreamHttpMethod": [ "Get" ],
      "DownstreamPathTemplate": "/Trips",
      "DownstreamScheme": "https",
      "DownstreamHostAndPorts": [
        {
          "Host": "localhost",
          "Port": "7001"
        }
      ]
    },
    {
      "UpstreamPathTemplate": "/gateway/trip/user-trips",
      "UpstreamHttpMethod": [ "Get" ],
      "DownstreamPathTemplate": "/Trips/UserTrips",
      "DownstreamScheme": "https",
      "DownstreamHostAndPorts": [
        {
          "Host": "localhost",
          "Port": "7001"
        }
      ]
    },
    {
      "UpstreamPathTemplate": "/gateway/trip/change-trip-date-range",
      "UpstreamHttpMethod": [ "Put" ],
      "DownstreamPathTemplate": "/Trips/ChangeDateRange",
      "DownstreamScheme": "https",
      "DownstreamHostAndPorts": [
        {
          "Host": "localhost",
          "Port": "7001"
        }
      ]
    },
    {
      "UpstreamPathTemplate": "/gateway/trip/add-day-to-tip",
      "UpstreamHttpMethod": [ "post" ],
      "DownstreamPathTemplate": "/Trips/AddDay",
      "DownstreamScheme": "https",
      "DownstreamHostAndPorts": [
        {
          "Host": "localhost",
          "Port": "7001"
        }
      ]
    },
    {
      "UpstreamPathTemplate": "/gateway/trip/remove-day-from-trip",
      "UpstreamHttpMethod": [ "delete" ],
      "DownstreamPathTemplate": "/Trips/RemoveDay",
      "DownstreamScheme": "https",
      "DownstreamHostAndPorts": [
        {
          "Host": "localhost",
          "Port": "7001"
        }
      ]
    },
    {
      "UpstreamPathTemplate": "/gateway/trip/add-activity-to-day",
      "UpstreamHttpMethod": [ "post" ],
      "DownstreamPathTemplate": "/Trips/AddActivity",
      "DownstreamScheme": "https",
      "DownstreamHostAndPorts": [
        {
          "Host": "localhost",
          "Port": "7001"
        }
      ]
    },
    {
      "UpstreamPathTemplate": "/gateway/trip/update-activity",
      "UpstreamHttpMethod": [ "put" ],
      "DownstreamPathTemplate": "/Trips/UpdateActivity",
      "DownstreamScheme": "https",
      "DownstreamHostAndPorts": [
        {
          "Host": "localhost",
          "Port": "7001"
        }
      ]
    }
  ]
}